{"web":{"client_id":"973500819258-0etd8ouhtgq904uo8p712sr3q0krtdk2.apps.googleusercontent.com","project_id":"nextjsfollow","auth_uri":"https://accounts.google.com/o/oauth2/auth","token_uri":"https://oauth2.googleapis.com/token","auth_provider_x509_cert_url":"https://www.googleapis.com/oauth2/v1/certs","client_secret":"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","redirect_uris":["http://localhost:3000","http://localhost:3000/api/auth/callback/google","http://localhost:8000","http://localhost:8000/account/google/callback"],"javascript_origins":["http://localhost:3000","http://localhost:8000"]}}